authx/__init__.py
authx/client.py
authx/config.py
authx/exceptions.py
authx/types.py
authx/utils.py
authx_sdk-0.1.0.dist-info/licenses/LICENSE
authx_sdk-0.1.0.dist-info/METADATA
authx_sdk-0.1.0.dist-info/WHEEL
authx_sdk-0.1.0.dist-info/top_level.txt
authx_sdk-0.1.0.dist-info/RECORD
