Metadata-Version: 2.4
Name: authx-sdk
Version: 0.1.0
Summary: AuthX SDK for OAuth2 token management
Author: Fawwaz Ali
Requires-Python: >=3.7
License-File: LICENSE
Requires-Dist: requests
Dynamic: license-file
